XingyuanTools/__init__.py
XingYuanTools-1.0.0.dist-info/LICENSE
XingYuanTools-1.0.0.dist-info/METADATA
XingYuanTools-1.0.0.dist-info/WHEEL
XingYuanTools-1.0.0.dist-info/top_level.txt
XingYuanTools-1.0.0.dist-info/RECORD
