Metadata-Version: 2.1
Name: XingYuanTools
Version: 1.0.0
Summary: Some tools and constants.
Home-page: https://github.com/pypa/sampleproject
Author: XY
Author-email: dus0963@outloo.com
License: UNKNOWN
Project-URL: Bug Tracker, https://github.com/pypa/sampleproject/issues
Platform: UNKNOWN
Classifier: Programming Language :: Python :: 3
Classifier: License :: OSI Approved :: MIT License
Classifier: Operating System :: OS Independent
Requires-Python: >=3.6
License-File: LICENSE
